aiokrpc/__init__.py
aiokrpc/exceptions.py
aiokrpc/protocol_schemas.py
aiokrpc/server.py
aio_krpc_server-0.0.7.dist-info/LICENSE
aio_krpc_server-0.0.7.dist-info/METADATA
aio_krpc_server-0.0.7.dist-info/WHEEL
aio_krpc_server-0.0.7.dist-info/top_level.txt
aio_krpc_server-0.0.7.dist-info/zip-safe
aio_krpc_server-0.0.7.dist-info/RECORD
