Metadata-Version: 2.1
Name: aio-krpc-server
Version: 0.0.7
Summary: Asyncio KRPC-server
Home-page: https://github.com/bashkirtsevich-llc/aiokrpc
Author: D.Bashkirtsevich
Author-email: bashkirtsevich@gmail.com
License: GPL3 License
Keywords: Async Kademlia RPC-server
Platform: UNKNOWN
Classifier: Programming Language :: Python
Requires-Python: >=3.6.*
Requires-Dist: aio-udp-server (==0.0.6)
Requires-Dist: Cerberus (==1.3.1)
Requires-Dist: py3-bencode (==0.0.3)
